engmanager_mcp/__init__.py
engmanager_mcp/server.py
engmanager_mcp/config/__init__.py
engmanager_mcp/config/settings.py
engmanager_mcp/resources/__init__.py
engmanager_mcp/resources/procedures.py
engmanager_mcp/tools/__init__.py
engmanager_mcp/tools/workflow.py
engmanager_mcp/utils/__init__.py
engmanager_mcp/utils/errors.py
engmanager_mcp/utils/parser.py
engmanager_mcp-1.0.2.dist-info/licenses/LICENSE
engmanager_mcp-1.0.2.dist-info/METADATA
engmanager_mcp-1.0.2.dist-info/WHEEL
engmanager_mcp-1.0.2.dist-info/entry_points.txt
engmanager_mcp-1.0.2.dist-info/top_level.txt
engmanager_mcp-1.0.2.dist-info/RECORD
