Metadata-Version: 2.4
Name: engmanager-mcp
Version: 1.0.2
Summary: MCP server providing workflow guidance and next-step instructions for LLM development workflows
Author-email: Simon Carr <simon.carr@gmail.com>
License: MIT
Project-URL: Homepage, https://github.com/scarr7981/engmanager-mcp
Project-URL: Documentation, https://github.com/scarr7981/engmanager-mcp/blob/main/README.md
Project-URL: Repository, https://github.com/scarr7981/engmanager-mcp
Project-URL: Issues, https://github.com/scarr7981/engmanager-mcp/issues
Keywords: mcp,workflow,development,llm,automation,procedures
Classifier: Development Status :: 4 - Beta
Classifier: Intended Audience :: Developers
Classifier: Topic :: Software Development :: Libraries :: Python Modules
Classifier: Topic :: Software Development :: Quality Assurance
Classifier: License :: OSI Approved :: MIT License
Classifier: Programming Language :: Python :: 3
Classifier: Programming Language :: Python :: 3.11
Classifier: Programming Language :: Python :: 3.12
Requires-Python: >=3.11
License-File: LICENSE
Requires-Dist: mcp>=1.0.0
Requires-Dist: pydantic>=2.5.0
Requires-Dist: pydantic-settings>=2.0.0
Requires-Dist: python-dotenv>=1.0.0
Provides-Extra: dev
Requires-Dist: pytest>=7.4.0; extra == "dev"
Requires-Dist: pytest-asyncio>=0.21.0; extra == "dev"
Requires-Dist: pytest-cov>=4.1.0; extra == "dev"
Requires-Dist: black>=23.0.0; extra == "dev"
Requires-Dist: ruff>=0.1.0; extra == "dev"
Requires-Dist: mypy>=1.7.0; extra == "dev"
Dynamic: license-file
